clever_selects/__init__.py
clever_selects/admin.py
clever_selects/form_fields.py
clever_selects/forms.py
clever_selects/views.py
clever_selects/widgets.py
clever_selects/static/js/clever-selects.js
clever_selects/templates/clever_selects/widgets/chained_select.html
clever_selects/templatetags/__init__.py
clever_selects/templatetags/clever_selects_extras.py
django_clever_selects-2.0.0.dist-info/licenses/LICENSE
django_clever_selects-2.0.0.dist-info/METADATA
django_clever_selects-2.0.0.dist-info/WHEEL
django_clever_selects-2.0.0.dist-info/top_level.txt
django_clever_selects-2.0.0.dist-info/RECORD
