Metadata-Version: 2.4
Name: django-clever-selects
Version: 2.0.0
Summary: Chained select box widget for Django framework using AJAX requests.
Home-page: https://github.com/PragmaticMates/django-clever-selects
Author: Pragmatic Mates
Author-email: info@pragmaticmates.com
Maintainer: Pragmatic Mates
Maintainer-email: info@pragmaticmates.com
License: BSD License
Keywords: django clever chained selects ajax
Classifier: Programming Language :: Python
Classifier: Operating System :: OS Independent
Classifier: Environment :: Web Environment
Classifier: Intended Audience :: Developers
Classifier: Framework :: Django
Classifier: License :: OSI Approved :: BSD License
Classifier: Development Status :: 5 - Production/Stable
License-File: LICENSE
Requires-Dist: django>=3
Dynamic: author
Dynamic: author-email
Dynamic: classifier
Dynamic: description
Dynamic: home-page
Dynamic: keywords
Dynamic: license
Dynamic: license-file
Dynamic: maintainer
Dynamic: maintainer-email
Dynamic: requires-dist
Dynamic: summary
